.conda-on-air.yaml
.gitignore
.pre-commit-config.yaml
.releaserc.json
CODE_OF_CONDUCT.md
Makefile
README.md
conda_on_air/__init__.py
conda_on_air/__main__.py
conda_on_air/conda_on_air.py
conda_on_air/errors.py
poetry.lock
pyproject.toml
conda_on_air-0.0.1.dist-info/LICENSE
conda_on_air-0.0.1.dist-info/METADATA
conda_on_air-0.0.1.dist-info/WHEEL
conda_on_air-0.0.1.dist-info/RECORD
